stereo/__init__.py
stereo/cli.py
stereo/generator.py
stereo/layout.py
stereo/fields/__init__.py
stereo/fields/base.py
stereo/fields/text.py
stereo-0.1.2.dist-info/DESCRIPTION.rst
stereo-0.1.2.dist-info/METADATA
stereo-0.1.2.dist-info/RECORD
stereo-0.1.2.dist-info/WHEEL
stereo-0.1.2.dist-info/entry_points.txt
stereo-0.1.2.dist-info/metadata.json
stereo-0.1.2.dist-info/top_level.txt
