Metadata-Version: 1.1
Name: stereo
Version: 0.1.2
Summary: Generate documents from CSV file in batch
Home-page: https://github.com/suda/stereo
Author: Wojtek Siudzinski
Author-email: admin@suda.pl
License: MIT
Keywords: pdf labels badges generator batch
Platform: UNKNOWN
Classifier: Development Status :: 3 - Alpha
Classifier: Intended Audience :: Developers
Classifier: Intended Audience :: End Users/Desktop
Classifier: Topic :: Office/Business
Classifier: Topic :: Utilities
Classifier: License :: OSI Approved :: MIT License
Classifier: Programming Language :: Python :: 2
Classifier: Programming Language :: Python :: 2.6
Classifier: Programming Language :: Python :: 2.7
Classifier: Programming Language :: Python :: 3
Classifier: Programming Language :: Python :: 3.3
Classifier: Programming Language :: Python :: 3.4
Classifier: Programming Language :: Python :: 3.5
